stimpool/__init__.py
stimpool/words/.DS_Store
stimpool/words/GPLv3.txt
stimpool/words/LGPLv2.1.txt
stimpool/words/LGPLv3.txt
stimpool/words/LICENSE.md
stimpool/words/META-INF/manifest.xml
stimpool/words/MPL-1.1.txt
stimpool/words/Puerto_Rico.png
stimpool/words/README.txt
stimpool/words/README_hyph_es.txt
stimpool/words/README_th_es.txt
stimpool/words/description.xml
stimpool/words/dictionaries.xcu
stimpool/words/es_PR.aff
stimpool/words/es_PR.dic
stimpool/words/hyph_es.dic
stimpool/words/package-description.txt
stimpool/words/th_es_v2.dat
stimpool/words/th_es_v2.idx
stimpool/words.py
stimpool-0.2.4.dist-info/entry_points.txt
stimpool-0.2.4.dist-info/LICENSE.rst
stimpool-0.2.4.dist-info/WHEEL
stimpool-0.2.4.dist-info/METADATA
stimpool-0.2.4.dist-info/RECORD
