Metadata-Version: 2.1
Name: stimpool
Version: 0.2.4
Summary: Create stimuli pools for psychological research
Home-page: https://github.com/mario-bermonti/stimpool
Keywords: stimpool
Author: Mario E. Bermonti Pérez
Author-email: mbermonti1132@gmail.com
Requires-Python: >=3.6.1,<3.10
Classifier: Development Status :: 2 - Pre-Alpha
Classifier: Intended Audience :: Developers
Classifier: License :: OSI Approved :: BSD License
Classifier: Natural Language :: English
Classifier: Programming Language :: Python :: 3
Classifier: Programming Language :: Python :: 3.6
Classifier: Programming Language :: Python :: 3.7
Classifier: Programming Language :: Python :: 3.8
Classifier: Programming Language :: Python :: 3.9
Requires-Dist: click (>=7.1.2,<8.0.0)
Requires-Dist: pandas
Requires-Dist: sphinx-markdown-tables (>=0.0.15,<0.0.16)
Project-URL: Bug Tracker, https://github.com/mario-bermonti/stimpool/issues
Project-URL: Documentation, https://stimpool.readthedocs.io/
Project-URL: Repository, https://github.com/mario-bermonti/stimpool
